wcmp/__init__.py
wcmp-1.1.dist-info/LICENSE
wcmp-1.1.dist-info/METADATA
wcmp-1.1.dist-info/WHEEL
wcmp-1.1.dist-info/top_level.txt
wcmp-1.1.dist-info/RECORD
