Metadata-Version: 2.1
Name: wcmp
Version: 1.1
Summary: A simple message plus package for notification via wechat.
Home-page: https://github.com/moshangsang24/wcmp
Author: moshangsang24
Author-email: liuyifan731@163.com
Classifier: Programming Language :: Python :: 3
Classifier: License :: OSI Approved :: MIT License
Classifier: Operating System :: OS Independent
License-File: LICENSE
